README.txt
setup.py
detsegtra.egg-info/PKG-INFO
detsegtra.egg-info/SOURCES.txt
detsegtra.egg-info/dependency_links.txt
detsegtra.egg-info/requires.txt
detsegtra.egg-info/top_level.txt
segtools/__init__.py
segtools/annotation.py
segtools/augmentation.py
segtools/cell_view_lib.py
segtools/color.py
segtools/graphmatch.py
segtools/ipython_bash.py
segtools/label_tools.py
segtools/math_utils.py
segtools/nhl_tools.py
segtools/numpy_utils.py
segtools/patchmaker.py
segtools/plotting.py
segtools/python_utils.py
segtools/render.py
segtools/scores_dense.py
segtools/spima.py
segtools/stack_segmentation.py
segtools/track_tools.py
segtools/track_vis.py
segtools/unet.py